{
  "id": "UG",
  "localization": {
    "UG_15.06_13-33_dome": {
      "__class__": "slab.psychoacoustics.Trialsequence",
      "label": "",
      "n_reps": 1,
      "conditions": [
        [
          0.0,
          -25.0
        ],
        [
          0.0,
          25.0
        ],
        [
          0.0,
          0.0
        ],
        [
          0.0,
          -25.0
        ],
        [
          0.0,
          37.5
        ],
        [
          0.0,
          -37.5
        ],
        [
          0.0,
          0.0
        ],
        [
          0.0,
          37.5
        ],
        [
          0.0,
          -37.5
        ],
        [
          0.0,
          12.5
        ],
        [
          0.0,
          -25.0
        ],
        [
          0.0,
          0.0
        ],
        [
          0.0,
          25.0
        ],
        [
          0.0,
          -37.5
        ],
        [
          0.0,
          25.0
        ],
        [
          0.0,
          -12.5
        ],
        [
          0.0,
          12.5
        ],
        [
          0.0,
          -12.5
        ],
        [
          0.0,
          12.5
        ],
        [
          0.0,
          37.5
        ],
        [
          0.0,
          -12.5
        ]
      ],
      "n_conditions": 21,
      "trials": [
        1,
        2,
        3,
        4,
        5,
        6,
        7,
        8,
        9,
        10,
        11,
        12,
        13,
        14,
        15,
        16,
        17,
        18,
        19,
        20,
        21
      ],
      "this_n": 21,
      "this_trial": [],
      "finished": true,
      "data": [
        [
          [
            [
              0.0,
              -0.03125
            ],
            [
              0.0,
              -25.0
            ]
          ]
        ],
        [
          [
            [
              0.0,
              12.84375
            ],
            [
              0.0,
              25.0
            ]
          ]
        ],
        [
          [
            [
              0.0,
              3.8125
            ],
            [
              0.0,
              0.0
            ]
          ]
        ],
        [
          [
            [
              -0.5,
              2.265625
            ],
            [
              0.0,
              -25.0
            ]
          ]
        ],
        [
          [
            [
              2.5,
              12.75
            ],
            [
              0.0,
              37.5
            ]
          ]
        ],
        [
          [
            [
              -1.0,
              2.9375
            ],
            [
              0.0,
              -37.5
            ]
          ]
        ],
        [
          [
            [
              2.0,
              6.609375
            ],
            [
              0.0,
              0.0
            ]
          ]
        ],
        [
          [
            [
              0.5,
              17.953125
            ],
            [
              0.0,
              37.5
            ]
          ]
        ],
        [
          [
            [
              -1.0,
              5.5
            ],
            [
              0.0,
              -37.5
            ]
          ]
        ],
        [
          [
            [
              4.0,
              11.96875
            ],
            [
              0.0,
              12.5
            ]
          ]
        ],
        [
          [
            [
              -1.0,
              1.671875
            ],
            [
              0.0,
              -25.0
            ]
          ]
        ],
        [
          [
            [
              1.5,
              0.953125
            ],
            [
              0.0,
              0.0
            ]
          ]
        ],
        [
          [
            [
              0.0,
              8.671875
            ],
            [
              0.0,
              25.0
            ]
          ]
        ],
        [
          [
            [
              0.0,
              0.59375
            ],
            [
              0.0,
              -37.5
            ]
          ]
        ],
        [
          [
            [
              3.0,
              6.875
            ],
            [
              0.0,
              25.0
            ]
          ]
        ],
        [
          [
            [
              -1.0,
              -4.484375
            ],
            [
              0.0,
              -12.5
            ]
          ]
        ],
        [
          [
            [
              1.5,
              1.53125
            ],
            [
              0.0,
              12.5
            ]
          ]
        ],
        [
          [
            [
              -2.0,
              -4.75
            ],
            [
              0.0,
              -12.5
            ]
          ]
        ],
        [
          [
            [
              1.5,
              5.40625
            ],
            [
              0.0,
              12.5
            ]
          ]
        ],
        [
          [
            [
              2.0,
              10.171875
            ],
            [
              0.0,
              37.5
            ]
          ]
        ],
        [
          [
            [
              -1.0,
              -5.09375
            ],
            [
              0.0,
              -12.5
            ]
          ]
        ]
      ],
      "n_trials": 21,
      "n_remaining": -1,
      "kind": "non_repeating",
      "settings": {
        "kind": "standard",
        "targets_per_speaker": 3,
        "min_distance": 15,
        "mode": "all_sources_repeated",
        "repeats": 3,
        "azimuth_range": [
          0.0,
          0.0
        ],
        "elevation_range": [
          -37.5,
          37.5
        ],
        "sector_size": [
          10.0,
          12.5
        ],
        "sector_centers": [
          [
            5.0,
            -31.25
          ],
          [
            5.0,
            -18.75
          ],
          [
            5.0,
            -6.25
          ],
          [
            5.0,
            6.25
          ],
          [
            5.0,
            18.75
          ],
          [
            5.0,
            31.25
          ]
        ]
      },
      "name": "UG_15.06_13-33_dome",
      "stim": "pinknoise_burst"
    },
    "UG_15.06_13-37_dome": {
      "__class__": "slab.psychoacoustics.Trialsequence",
      "label": "",
      "n_reps": 1,
      "conditions": [
        [
          0.0,
          -12.5
        ],
        [
          0.0,
          12.5
        ],
        [
          0.0,
          -25.0
        ],
        [
          0.0,
          12.5
        ],
        [
          0.0,
          -25.0
        ],
        [
          0.0,
          12.5
        ],
        [
          0.0,
          37.5
        ],
        [
          0.0,
          -25.0
        ],
        [
          0.0,
          37.5
        ],
        [
          0.0,
          0.0
        ],
        [
          0.0,
          25.0
        ],
        [
          0.0,
          -12.5
        ],
        [
          0.0,
          25.0
        ],
        [
          0.0,
          0.0
        ],
        [
          0.0,
          -37.5
        ],
        [
          0.0,
          0.0
        ],
        [
          0.0,
          25.0
        ],
        [
          0.0,
          -12.5
        ],
        [
          0.0,
          -37.5
        ],
        [
          0.0,
          37.5
        ],
        [
          0.0,
          -37.5
        ]
      ],
      "n_conditions": 21,
      "trials": [
        1,
        2,
        3,
        4,
        5,
        6,
        7,
        8,
        9,
        10,
        11,
        12,
        13,
        14,
        15,
        16,
        17,
        18,
        19,
        20,
        21
      ],
      "this_n": 21,
      "this_trial": [],
      "finished": true,
      "data": [
        [
          [
            [
              -1.5,
              -9.6484375
            ],
            [
              0.0,
              -12.5
            ]
          ]
        ],
        [
          [
            [
              0.625,
              15.65625
            ],
            [
              0.0,
              12.5
            ]
          ]
        ],
        [
          [
            [
              -0.875,
              -22.28125
            ],
            [
              0.0,
              -25.0
            ]
          ]
        ],
        [
          [
            [
              0.25,
              15.828125
            ],
            [
              0.0,
              12.5
            ]
          ]
        ],
        [
          [
            [
              -2.25,
              -28.6875
            ],
            [
              0.0,
              -25.0
            ]
          ]
        ],
        [
          [
            [
              0.5,
              15.578125
            ],
            [
              0.0,
              12.5
            ]
          ]
        ],
        [
          [
            [
              1.125,
              32.1875
            ],
            [
              0.0,
              37.5
            ]
          ]
        ],
        [
          [
            [
              -1.75,
              -34.21875
            ],
            [
              0.0,
              -25.0
            ]
          ]
        ],
        [
          [
            [
              1.125,
              36.59375
            ],
            [
              0.0,
              37.5
            ]
          ]
        ],
        [
          [
            [
              -0.125,
              3.046875
            ],
            [
              0.0,
              0.0
            ]
          ]
        ],
        [
          [
            [
              -0.125,
              4.015625
            ],
            [
              0.0,
              25.0
            ]
          ]
        ],
        [
          [
            [
              -1.25,
              -22.03125
            ],
            [
              0.0,
              -12.5
            ]
          ]
        ],
        [
          [
            [
              0.5,
              13.5625
            ],
            [
              0.0,
              25.0
            ]
          ]
        ],
        [
          [
            [
              -0.875,
              -25.625
            ],
            [
              0.0,
              0.0
            ]
          ]
        ],
        [
          [
            [
              -0.75,
              4.203125
            ],
            [
              0.0,
              -37.5
            ]
          ]
        ],
        [
          [
            [
              -1.125,
              -15.375
            ],
            [
              0.0,
              0.0
            ]
          ]
        ],
        [
          [
            [
              -0.25,
              6.109375
            ],
            [
              0.0,
              25.0
            ]
          ]
        ],
        [
          [
            [
              -1.625,
              -22.515625
            ],
            [
              0.0,
              -12.5
            ]
          ]
        ],
        [
          [
            [
              -1.75,
              -35.4375
            ],
            [
              0.0,
              -37.5
            ]
          ]
        ],
        [
          [
            [
              1.0,
              32.125
            ],
            [
              0.0,
              37.5
            ]
          ]
        ],
        [
          [
            [
              -0.875,
              -35.5
            ],
            [
              0.0,
              -37.5
            ]
          ]
        ]
      ],
      "n_trials": 21,
      "n_remaining": -1,
      "kind": "non_repeating",
      "settings": {
        "kind": "standard",
        "targets_per_speaker": 3,
        "min_distance": 15,
        "mode": "all_sources_repeated",
        "repeats": 3,
        "azimuth_range": [
          0.0,
          0.0
        ],
        "elevation_range": [
          -37.5,
          37.5
        ],
        "sector_size": [
          10.0,
          12.5
        ],
        "sector_centers": [
          [
            5.0,
            -31.25
          ],
          [
            5.0,
            -18.75
          ],
          [
            5.0,
            -6.25
          ],
          [
            5.0,
            6.25
          ],
          [
            5.0,
            18.75
          ],
          [
            5.0,
            31.25
          ]
        ]
      },
      "name": "UG_15.06_13-37_dome",
      "stim": "pinknoise_burst"
    },
    "UG_15.06_13-41_dome": {
      "__class__": "slab.psychoacoustics.Trialsequence",
      "label": "",
      "n_reps": 1,
      "conditions": [
        [
          0.0,
          -12.5
        ],
        [
          0.0,
          37.5
        ],
        [
          0.0,
          0.0
        ],
        [
          0.0,
          -25.0
        ],
        [
          0.0,
          0.0
        ],
        [
          0.0,
          -25.0
        ],
        [
          0.0,
          0.0
        ],
        [
          0.0,
          37.5
        ],
        [
          0.0,
          -25.0
        ],
        [
          0.0,
          25.0
        ],
        [
          0.0,
          -37.5
        ],
        [
          0.0,
          12.5
        ],
        [
          0.0,
          -37.5
        ],
        [
          0.0,
          25.0
        ],
        [
          0.0,
          -37.5
        ],
        [
          0.0,
          25.0
        ],
        [
          0.0,
          -12.5
        ],
        [
          0.0,
          12.5
        ],
        [
          0.0,
          -12.5
        ],
        [
          0.0,
          12.5
        ],
        [
          0.0,
          37.5
        ]
      ],
      "n_conditions": 21,
      "trials": [
        1,
        2,
        3,
        4,
        5,
        6,
        7,
        8,
        9,
        10,
        11,
        12,
        13,
        14,
        15,
        16,
        17,
        18,
        19,
        20,
        21
      ],
      "this_n": 21,
      "this_trial": [],
      "finished": true,
      "data": [
        [
          [
            [
              -0.5,
              -5.828125
            ],
            [
              0.0,
              -12.5
            ]
          ]
        ],
        [
          [
            [
              1.5,
              26.1875
            ],
            [
              0.0,
              37.5
            ]
          ]
        ],
        [
          [
            [
              -1.0,
              -12.0859375
            ],
            [
              0.0,
              0.0
            ]
          ]
        ],
        [
          [
            [
              -1.0,
              -5.265625
            ],
            [
              0.0,
              -25.0
            ]
          ]
        ],
        [
          [
            [
              0.5,
              6.296875
            ],
            [
              0.0,
              0.0
            ]
          ]
        ],
        [
          [
            [
              -0.625,
              -6.0625
            ],
            [
              0.0,
              -25.0
            ]
          ]
        ],
        [
          [
            [
              0.0,
              0.03125
            ],
            [
              0.0,
              0.0
            ]
          ]
        ],
        [
          [
            [
              0.5,
              12.609375
            ],
            [
              0.0,
              37.5
            ]
          ]
        ],
        [
          [
            [
              -0.375,
              -18.59375
            ],
            [
              0.0,
              -25.0
            ]
          ]
        ],
        [
          [
            [
              -0.125,
              14.40625
            ],
            [
              0.0,
              25.0
            ]
          ]
        ],
        [
          [
            [
              -0.5,
              -18.28125
            ],
            [
              0.0,
              -37.5
            ]
          ]
        ],
        [
          [
            [
              -0.125,
              6.28125
            ],
            [
              0.0,
              12.5
            ]
          ]
        ],
        [
          [
            [
              -1.0,
              -12.0703125
            ],
            [
              0.0,
              -37.5
            ]
          ]
        ],
        [
          [
            [
              0.0,
              7.40625
            ],
            [
              0.0,
              25.0
            ]
          ]
        ],
        [
          [
            [
              -0.5,
              -23.75
            ],
            [
              0.0,
              -37.5
            ]
          ]
        ],
        [
          [
            [
              0.125,
              6.8125
            ],
            [
              0.0,
              25.0
            ]
          ]
        ],
        [
          [
            [
              -1.0,
              -13.53125
            ],
            [
              0.0,
              -12.5
            ]
          ]
        ],
        [
          [
            [
              0.0,
              6.359375
            ],
            [
              0.0,
              12.5
            ]
          ]
        ],
        [
          [
            [
              -1.0,
              -13.03125
            ],
            [
              0.0,
              -12.5
            ]
          ]
        ],
        [
          [
            [
              0.0,
              6.40625
            ],
            [
              0.0,
              12.5
            ]
          ]
        ],
        [
          [
            [
              0.375,
              22.046875
            ],
            [
              0.0,
              37.5
            ]
          ]
        ]
      ],
      "n_trials": 21,
      "n_remaining": -1,
      "kind": "non_repeating",
      "settings": {
        "kind": "standard",
        "targets_per_speaker": 3,
        "min_distance": 15,
        "mode": "all_sources_repeated",
        "repeats": 3,
        "azimuth_range": [
          0.0,
          0.0
        ],
        "elevation_range": [
          -37.5,
          37.5
        ],
        "sector_size": [
          10.0,
          12.5
        ],
        "sector_centers": [
          [
            5.0,
            -31.25
          ],
          [
            5.0,
            -18.75
          ],
          [
            5.0,
            -6.25
          ],
          [
            5.0,
            6.25
          ],
          [
            5.0,
            18.75
          ],
          [
            5.0,
            31.25
          ]
        ]
      },
      "name": "UG_15.06_13-41_dome",
      "stim": "pinknoise_burst"
    },
    "UG_15.06_13-46_dome": {
      "__class__": "slab.psychoacoustics.Trialsequence",
      "label": "",
      "n_reps": 1,
      "conditions": [
        [
          0.0,
          25.0
        ],
        [
          0.0,
          -37.5
        ],
        [
          0.0,
          -12.5
        ],
        [
          0.0,
          -37.5
        ],
        [
          0.0,
          37.5
        ],
        [
          0.0,
          0.0
        ],
        [
          0.0,
          25.0
        ],
        [
          0.0,
          -12.5
        ],
        [
          0.0,
          -37.5
        ],
        [
          0.0,
          37.5
        ],
        [
          0.0,
          -25.0
        ],
        [
          0.0,
          12.5
        ],
        [
          0.0,
          -25.0
        ],
        [
          0.0,
          25.0
        ],
        [
          0.0,
          0.0
        ],
        [
          0.0,
          37.5
        ],
        [
          0.0,
          0.0
        ],
        [
          0.0,
          -25.0
        ],
        [
          0.0,
          12.5
        ],
        [
          0.0,
          -12.5
        ],
        [
          0.0,
          12.5
        ]
      ],
      "n_conditions": 21,
      "trials": [
        1,
        2,
        3,
        4,
        5,
        6,
        7,
        8,
        9,
        10,
        11,
        12,
        13,
        14,
        15,
        16,
        17,
        18,
        19,
        20,
        21
      ],
      "this_n": 21,
      "this_trial": [],
      "finished": true,
      "data": [
        [
          [
            [
              0.625,
              6.5625
            ],
            [
              0.0,
              25.0
            ]
          ]
        ],
        [
          [
            [
              -3.125,
              -23.59375
            ],
            [
              0.0,
              -37.5
            ]
          ]
        ],
        [
          [
            [
              -2.5,
              -17.578125
            ],
            [
              0.0,
              -12.5
            ]
          ]
        ],
        [
          [
            [
              0.25,
              4.3125
            ],
            [
              0.0,
              -37.5
            ]
          ]
        ],
        [
          [
            [
              1.875,
              17.4375
            ],
            [
              0.0,
              37.5
            ]
          ]
        ],
        [
          [
            [
              -0.625,
              -3.640625
            ],
            [
              0.0,
              0.0
            ]
          ]
        ],
        [
          [
            [
              2.25,
              21.84375
            ],
            [
              0.0,
              25.0
            ]
          ]
        ],
        [
          [
            [
              -1.625,
              -14.59375
            ],
            [
              0.0,
              -12.5
            ]
          ]
        ],
        [
          [
            [
              -2.0,
              -33.625
            ],
            [
              0.0,
              -37.5
            ]
          ]
        ],
        [
          [
            [
              2.75,
              33.3125
            ],
            [
              0.0,
              37.5
            ]
          ]
        ],
        [
          [
            [
              -3.25,
              -36.1875
            ],
            [
              0.0,
              -25.0
            ]
          ]
        ],
        [
          [
            [
              0.5,
              11.15625
            ],
            [
              0.0,
              12.5
            ]
          ]
        ],
        [
          [
            [
              -2.25,
              -25.421875
            ],
            [
              0.0,
              -25.0
            ]
          ]
        ],
        [
          [
            [
              0.375,
              9.765625
            ],
            [
              0.0,
              25.0
            ]
          ]
        ],
        [
          [
            [
              -2.125,
              -26.515625
            ],
            [
              0.0,
              0.0
            ]
          ]
        ],
        [
          [
            [
              1.5,
              18.46875
            ],
            [
              0.0,
              37.5
            ]
          ]
        ],
        [
          [
            [
              -2.875,
              -31.34375
            ],
            [
              0.0,
              0.0
            ]
          ]
        ],
        [
          [
            [
              0.0,
              -2.6875
            ],
            [
              0.0,
              -25.0
            ]
          ]
        ],
        [
          [
            [
              0.625,
              8.90625
            ],
            [
              0.0,
              12.5
            ]
          ]
        ],
        [
          [
            [
              -1.5,
              -15.28125
            ],
            [
              0.0,
              -12.5
            ]
          ]
        ],
        [
          [
            [
              1.375,
              16.890625
            ],
            [
              0.0,
              12.5
            ]
          ]
        ]
      ],
      "n_trials": 21,
      "n_remaining": -1,
      "kind": "non_repeating",
      "settings": {
        "kind": "standard",
        "targets_per_speaker": 3,
        "min_distance": 15,
        "mode": "all_sources_repeated",
        "repeats": 3,
        "azimuth_range": [
          0.0,
          0.0
        ],
        "elevation_range": [
          -37.5,
          37.5
        ],
        "sector_size": [
          10.0,
          12.5
        ],
        "sector_centers": [
          [
            5.0,
            -31.25
          ],
          [
            5.0,
            -18.75
          ],
          [
            5.0,
            -6.25
          ],
          [
            5.0,
            6.25
          ],
          [
            5.0,
            18.75
          ],
          [
            5.0,
            31.25
          ]
        ]
      },
      "name": "UG_15.06_13-46_dome",
      "stim": "pinknoise_burst"
    },
    "UG_15.06_13-50_UG": {
      "__class__": "slab.psychoacoustics.Trialsequence",
      "label": "",
      "n_reps": 1,
      "conditions": [
        [
          0.0,
          -4.17
        ],
        [
          0.0,
          -20.83
        ],
        [
          0.0,
          8.33
        ],
        [
          0.0,
          -12.5
        ],
        [
          0.0,
          25.0
        ],
        [
          0.0,
          -16.67
        ],
        [
          0.0,
          4.17
        ],
        [
          0.0,
          -33.34
        ],
        [
          0.0,
          8.33
        ],
        [
          0.0,
          -25.0
        ],
        [
          0.0,
          29.17
        ],
        [
          0.0,
          -33.34
        ],
        [
          0.0,
          -8.33
        ],
        [
          0.0,
          33.34
        ],
        [
          0.0,
          0.0
        ],
        [
          0.0,
          16.67
        ],
        [
          0.0,
          0.0
        ],
        [
          0.0,
          33.34
        ],
        [
          0.0,
          -25.0
        ],
        [
          0.0,
          25.0
        ],
        [
          0.0,
          -8.33
        ],
        [
          0.0,
          20.83
        ],
        [
          0.0,
          -29.17
        ],
        [
          0.0,
          16.67
        ],
        [
          0.0,
          -29.17
        ],
        [
          0.0,
          20.83
        ],
        [
          0.0,
          4.17
        ],
        [
          0.0,
          -12.5
        ],
        [
          0.0,
          29.17
        ],
        [
          0.0,
          -4.17
        ],
        [
          0.0,
          -20.83
        ],
        [
          0.0,
          12.5
        ],
        [
          0.0,
          -16.67
        ],
        [
          0.0,
          12.5
        ]
      ],
      "n_conditions": 34,
      "trials": [
        1,
        2,
        3,
        4,
        5,
        6,
        7,
        8,
        9,
        10,
        11,
        12,
        13,
        14,
        15,
        16,
        17,
        18,
        19,
        20,
        21,
        22,
        23,
        24,
        25,
        26,
        27,
        28,
        29,
        30,
        31,
        32,
        33,
        34
      ],
      "this_n": 34,
      "this_trial": [],
      "finished": true,
      "data": [
        [
          [
            [
              0.125,
              5.484375
            ],
            [
              0.0,
              -4.17
            ]
          ]
        ],
        [
          [
            [
              0.75,
              4.8046875
            ],
            [
              0.0,
              -20.83
            ]
          ]
        ],
        [
          [
            [
              0.25,
              10.3671875
            ],
            [
              0.0,
              8.33
            ]
          ]
        ],
        [
          [
            [
              -1.125,
              -9.3125
            ],
            [
              0.0,
              -12.5
            ]
          ]
        ],
        [
          [
            [
              1.0,
              18.9375
            ],
            [
              0.0,
              25.0
            ]
          ]
        ],
        [
          [
            [
              0.0,
              4.484375
            ],
            [
              0.0,
              -16.67
            ]
          ]
        ],
        [
          [
            [
              1.0,
              14.265625
            ],
            [
              0.0,
              4.17
            ]
          ]
        ],
        [
          [
            [
              -1.375,
              -22.40625
            ],
            [
              0.0,
              -33.34
            ]
          ]
        ],
        [
          [
            [
              0.875,
              12.5703125
            ],
            [
              0.0,
              8.33
            ]
          ]
        ],
        [
          [
            [
              -2.25,
              -24.21875
            ],
            [
              0.0,
              -25.0
            ]
          ]
        ],
        [
          [
            [
              1.625,
              18.34375
            ],
            [
              0.0,
              29.17
            ]
          ]
        ],
        [
          [
            [
              -2.375,
              -31.71875
            ],
            [
              0.0,
              -33.34
            ]
          ]
        ],
        [
          [
            [
              0.25,
              8.578125
            ],
            [
              0.0,
              -8.33
            ]
          ]
        ],
        [
          [
            [
              1.5,
              20.1875
            ],
            [
              0.0,
              33.34
            ]
          ]
        ],
        [
          [
            [
              0.5,
              10.171875
            ],
            [
              0.0,
              0.0
            ]
          ]
        ],
        [
          [
            [
              1.75,
              23.609375
            ],
            [
              0.0,
              16.67
            ]
          ]
        ],
        [
          [
            [
              0.5,
              11.484375
            ],
            [
              0.0,
              0.0
            ]
          ]
        ],
        [
          [
            [
              1.75,
              24.84375
            ],
            [
              0.0,
              33.34
            ]
          ]
        ],
        [
          [
            [
              -2.5,
              -35.3125
            ],
            [
              0.0,
              -25.0
            ]
          ]
        ],
        [
          [
            [
              1.75,
              28.0625
            ],
            [
              0.0,
              25.0
            ]
          ]
        ],
        [
          [
            [
              0.125,
              4.1171875
            ],
            [
              0.0,
              -8.33
            ]
          ]
        ],
        [
          [
            [
              2.75,
              28.96875
            ],
            [
              0.0,
              20.83
            ]
          ]
        ],
        [
          [
            [
              -2.125,
              -27.375
            ],
            [
              0.0,
              -29.17
            ]
          ]
        ],
        [
          [
            [
              2.75,
              32.875
            ],
            [
              0.0,
              16.67
            ]
          ]
        ],
        [
          [
            [
              -2.375,
              -36.875
            ],
            [
              0.0,
              -29.17
            ]
          ]
        ],
        [
          [
            [
              -20.25,
              -26.4375
            ],
            [
              0.0,
              20.83
            ]
          ]
        ],
        [
          [
            [
              -1.375,
              -22.5625
            ],
            [
              0.0,
              4.17
            ]
          ]
        ],
        [
          [
            [
              1.125,
              5.3125
            ],
            [
              0.0,
              -12.5
            ]
          ]
        ],
        [
          [
            [
              3.125,
              27.46875
            ],
            [
              0.0,
              29.17
            ]
          ]
        ],
        [
          [
            [
              -0.625,
              -12.875
            ],
            [
              0.0,
              -4.17
            ]
          ]
        ],
        [
          [
            [
              0.125,
              -2.4609375
            ],
            [
              0.0,
              -20.83
            ]
          ]
        ],
        [
          [
            [
              1.125,
              7.1171875
            ],
            [
              0.0,
              12.5
            ]
          ]
        ],
        [
          [
            [
              -1.0,
              -23.515625
            ],
            [
              0.0,
              -16.67
            ]
          ]
        ],
        [
          [
            [
              1.5,
              1.2578125
            ],
            [
              0.0,
              12.5
            ]
          ]
        ]
      ],
      "n_trials": 34,
      "n_remaining": -1,
      "kind": "non_repeating",
      "settings": {
        "kind": "standard",
        "azimuth_range": [
          -1,
          1
        ],
        "elevation_range": [
          -35,
          35
        ],
        "targets_per_speaker": 2,
        "min_distance": 15,
        "gain": 0.2,
        "stim": "noise",
        "mode": "all_sources_repeated",
        "repeats": 2,
        "sector_size": [
          2.0,
          4.156199999999998
        ],
        "sector_centers": [
          [
            0.0,
            -32.9219
          ],
          [
            0.0,
            -28.765700000000002
          ],
          [
            0.0,
            -24.609500000000004
          ],
          [
            0.0,
            -20.453300000000006
          ],
          [
            0.0,
            -16.297100000000007
          ],
          [
            0.0,
            -12.14090000000001
          ],
          [
            0.0,
            -7.984700000000011
          ],
          [
            0.0,
            -3.8285000000000124
          ],
          [
            0.0,
            0.3276999999999859
          ],
          [
            0.0,
            4.483899999999984
          ],
          [
            0.0,
            8.640099999999983
          ],
          [
            0.0,
            12.796299999999981
          ],
          [
            0.0,
            16.95249999999998
          ],
          [
            0.0,
            21.108699999999978
          ],
          [
            0.0,
            25.264899999999976
          ],
          [
            0.0,
            29.421099999999967
          ],
          [
            0.0,
            33.57729999999998
          ]
        ]
      },
      "name": "UG_15.06_13-50_UG",
      "hrir": "UG",
      "ear": null,
      "mirrored": false,
      "stim": "noise",
      "hp": "DT990",
      "response_errors": [
        [
          0.0,
          -32.9219,
          7.815860177389308,
          0.03743653316954299
        ],
        [
          0.0,
          -28.765700000000002,
          5.594150963282989,
          0.0267949545333765
        ],
        [
          0.0,
          -24.609500000000004,
          7.312934014897851,
          0.03502760932282298
        ],
        [
          0.0,
          -20.453300000000006,
          22.299771975869646,
          0.10681180756827996
        ],
        [
          0.0,
          -16.297100000000007,
          15.722120774266587,
          0.07530606772676336
        ],
        [
          0.0,
          -12.14090000000001,
          12.795415438742113,
          0.06128768729465102
        ],
        [
          0.0,
          -7.984700000000011,
          14.846163943520581,
          0.07111039556720022
        ],
        [
          0.0,
          -3.8285000000000124,
          9.191952503157992,
          0.04402776239176285
        ],
        [
          0.0,
          0.3276999999999859,
          10.847993135973354,
          0.051959892531431184
        ],
        [
          0.0,
          4.483899999999984,
          20.205793728416428,
          0.09678203677684948
        ],
        [
          0.0,
          8.640099999999983,
          3.3264382609491263,
          0.015933027647131615
        ],
        [
          0.0,
          12.796299999999981,
          8.813666949553758,
          0.042215844144295654
        ],
        [
          0.0,
          16.95249999999998,
          12.465090260215225,
          0.05970549042546552
        ],
        [
          0.0,
          21.108699999999978,
          33.91501000893631,
          0.16244666208563427
        ],
        [
          0.0,
          25.264899999999976,
          4.802749863359532,
          0.023004288777429778
        ],
        [
          0.0,
          29.421099999999967,
          7.749256113492444,
          0.037117511949778255
        ],
        [
          0.0,
          33.57729999999998,
          11.071913120877081,
          0.05303242808758439
        ]
      ]
    },
    "UG_16.06_09-36_dome": {
      "__class__": "slab.psychoacoustics.Trialsequence",
      "label": "",
      "n_reps": 1,
      "conditions": [
        [
          0.0,
          -37.5
        ],
        [
          0.0,
          12.5
        ],
        [
          0.0,
          -25.0
        ],
        [
          0.0,
          25.0
        ],
        [
          0.0,
          0.0
        ],
        [
          0.0,
          25.0
        ],
        [
          0.0,
          -25.0
        ],
        [
          0.0,
          37.5
        ],
        [
          0.0,
          0.0
        ],
        [
          0.0,
          -25.0
        ],
        [
          0.0,
          12.5
        ],
        [
          0.0,
          -12.5
        ],
        [
          0.0,
          37.5
        ],
        [
          0.0,
          -12.5
        ],
        [
          0.0,
          12.5
        ],
        [
          0.0,
          -37.5
        ],
        [
          0.0,
          37.5
        ],
        [
          0.0,
          -12.5
        ],
        [
          0.0,
          25.0
        ],
        [
          0.0,
          0.0
        ],
        [
          0.0,
          -37.5
        ]
      ],
      "n_conditions": 21,
      "trials": [
        1,
        2,
        3,
        4,
        5,
        6,
        7,
        8,
        9,
        10,
        11,
        12,
        13,
        14,
        15,
        16,
        17,
        18,
        19,
        20,
        21
      ],
      "this_n": 5,
      "this_trial": [
        0.0,
        25.0
      ],
      "finished": false,
      "data": [
        [
          [
            [
              -1.25,
              -20.78125
            ],
            [
              0.0,
              -37.5
            ]
          ]
        ],
        [
          [
            [
              4.75,
              20.59375
            ],
            [
              0.0,
              12.5
            ]
          ]
        ],
        [
          [
            [
              -0.375,
              -15.5546875
            ],
            [
              0.0,
              -25.0
            ]
          ]
        ],
        [
          [
            [
              5.0,
              16.625
            ],
            [
              0.0,
              25.0
            ]
          ]
        ],
        [
          [
            [
              1.0,
              10.1875
            ],
            [
              0.0,
              0.0
            ]
          ]
        ],
        [],
        [],
        [],
        [],
        [],
        [],
        [],
        [],
        [],
        [],
        [],
        [],
        [],
        [],
        [],
        []
      ],
      "n_trials": 21,
      "n_remaining": 15,
      "kind": "non_repeating",
      "settings": {
        "kind": "standard",
        "targets_per_speaker": 3,
        "min_distance": 15,
        "mode": "all_sources_repeated",
        "repeats": 3,
        "azimuth_range": [
          0.0,
          0.0
        ],
        "elevation_range": [
          -37.5,
          37.5
        ],
        "sector_size": [
          10.0,
          12.5
        ],
        "sector_centers": [
          [
            5.0,
            -31.25
          ],
          [
            5.0,
            -18.75
          ],
          [
            5.0,
            -6.25
          ],
          [
            5.0,
            6.25
          ],
          [
            5.0,
            18.75
          ],
          [
            5.0,
            31.25
          ]
        ]
      },
      "name": "UG_16.06_09-36_dome",
      "stim": "pinknoise_burst"
    },
    "UG_16.06_09-39_dome": {
      "__class__": "slab.psychoacoustics.Trialsequence",
      "label": "",
      "n_reps": 1,
      "conditions": [
        [
          0.0,
          0.0
        ],
        [
          0.0,
          -37.5
        ],
        [
          0.0,
          12.5
        ],
        [
          0.0,
          -25.0
        ],
        [
          0.0,
          37.5
        ],
        [
          0.0,
          -12.5
        ],
        [
          0.0,
          12.5
        ],
        [
          0.0,
          -37.5
        ],
        [
          0.0,
          12.5
        ],
        [
          0.0,
          -25.0
        ],
        [
          0.0,
          25.0
        ],
        [
          0.0,
          0.0
        ],
        [
          0.0,
          37.5
        ],
        [
          0.0,
          -25.0
        ],
        [
          0.0,
          0.0
        ],
        [
          0.0,
          25.0
        ],
        [
          0.0,
          -12.5
        ],
        [
          0.0,
          25.0
        ],
        [
          0.0,
          -12.5
        ],
        [
          0.0,
          -37.5
        ],
        [
          0.0,
          37.5
        ]
      ],
      "n_conditions": 21,
      "trials": [
        1,
        2,
        3,
        4,
        5,
        6,
        7,
        8,
        9,
        10,
        11,
        12,
        13,
        14,
        15,
        16,
        17,
        18,
        19,
        20,
        21
      ],
      "this_n": 21,
      "this_trial": [],
      "finished": true,
      "data": [
        [
          [
            [
              1.5,
              9.5625
            ],
            [
              0.0,
              0.0
            ]
          ]
        ],
        [
          [
            [
              1.125,
              -18.125
            ],
            [
              0.0,
              -37.5
            ]
          ]
        ],
        [
          [
            [
              2.25,
              18.96875
            ],
            [
              0.0,
              12.5
            ]
          ]
        ],
        [
          [
            [
              -0.75,
              -10.5859375
            ],
            [
              0.0,
              -25.0
            ]
          ]
        ],
        [
          [
            [
              4.25,
              29.8125
            ],
            [
              0.0,
              37.5
            ]
          ]
        ],
        [
          [
            [
              0.5,
              -4.8671875
            ],
            [
              0.0,
              -12.5
            ]
          ]
        ],
        [
          [
            [
              1.75,
              11.140625
            ],
            [
              0.0,
              12.5
            ]
          ]
        ],
        [
          [
            [
              0.75,
              -20.53125
            ],
            [
              0.0,
              -37.5
            ]
          ]
        ],
        [
          [
            [
              1.75,
              9.515625
            ],
            [
              0.0,
              12.5
            ]
          ]
        ],
        [
          [
            [
              -0.375,
              -11.328125
            ],
            [
              0.0,
              -25.0
            ]
          ]
        ],
        [
          [
            [
              1.75,
              13.859375
            ],
            [
              0.0,
              25.0
            ]
          ]
        ],
        [
          [
            [
              1.5,
              5.4453125
            ],
            [
              0.0,
              0.0
            ]
          ]
        ],
        [
          [
            [
              3.5,
              29.765625
            ],
            [
              0.0,
              37.5
            ]
          ]
        ],
        [
          [
            [
              -0.5,
              -21.515625
            ],
            [
              0.0,
              -25.0
            ]
          ]
        ],
        [
          [
            [
              1.0,
              8.765625
            ],
            [
              0.0,
              0.0
            ]
          ]
        ],
        [
          [
            [
              1.25,
              16.71875
            ],
            [
              0.0,
              25.0
            ]
          ]
        ],
        [
          [
            [
              0.75,
              3.703125
            ],
            [
              0.0,
              -12.5
            ]
          ]
        ],
        [
          [
            [
              1.75,
              11.953125
            ],
            [
              0.0,
              25.0
            ]
          ]
        ],
        [
          [
            [
              1.25,
              2.2109375
            ],
            [
              0.0,
              -12.5
            ]
          ]
        ],
        [
          [
            [
              0.875,
              -26.78125
            ],
            [
              0.0,
              -37.5
            ]
          ]
        ],
        [
          [
            [
              2.875,
              28.25
            ],
            [
              0.0,
              37.5
            ]
          ]
        ]
      ],
      "n_trials": 21,
      "n_remaining": -1,
      "kind": "non_repeating",
      "settings": {
        "kind": "standard",
        "targets_per_speaker": 3,
        "min_distance": 15,
        "mode": "all_sources_repeated",
        "repeats": 3,
        "azimuth_range": [
          0.0,
          0.0
        ],
        "elevation_range": [
          -37.5,
          37.5
        ],
        "sector_size": [
          10.0,
          12.5
        ],
        "sector_centers": [
          [
            5.0,
            -31.25
          ],
          [
            5.0,
            -18.75
          ],
          [
            5.0,
            -6.25
          ],
          [
            5.0,
            6.25
          ],
          [
            5.0,
            18.75
          ],
          [
            5.0,
            31.25
          ]
        ]
      },
      "name": "UG_16.06_09-39_dome",
      "stim": "pinknoise_burst"
    },
    "UG_16.06_09-42_dome": {
      "__class__": "slab.psychoacoustics.Trialsequence",
      "label": "",
      "n_reps": 1,
      "conditions": [
        [
          0.0,
          -25.0
        ],
        [
          0.0,
          25.0
        ],
        [
          0.0,
          -37.5
        ],
        [
          0.0,
          -12.5
        ],
        [
          0.0,
          12.5
        ],
        [
          0.0,
          -12.5
        ],
        [
          0.0,
          37.5
        ],
        [
          0.0,
          12.5
        ],
        [
          0.0,
          37.5
        ],
        [
          0.0,
          -25.0
        ],
        [
          0.0,
          12.5
        ],
        [
          0.0,
          -12.5
        ],
        [
          0.0,
          37.5
        ],
        [
          0.0,
          0.0
        ],
        [
          0.0,
          -37.5
        ],
        [
          0.0,
          0.0
        ],
        [
          0.0,
          25.0
        ],
        [
          0.0,
          -37.5
        ],
        [
          0.0,
          0.0
        ],
        [
          0.0,
          -25.0
        ],
        [
          0.0,
          25.0
        ]
      ],
      "n_conditions": 21,
      "trials": [
        1,
        2,
        3,
        4,
        5,
        6,
        7,
        8,
        9,
        10,
        11,
        12,
        13,
        14,
        15,
        16,
        17,
        18,
        19,
        20,
        21
      ],
      "this_n": 8,
      "this_trial": [
        0.0,
        37.5
      ],
      "finished": false,
      "data": [
        [
          [
            [
              -1.75,
              -2.5625
            ],
            [
              0.0,
              -25.0
            ]
          ]
        ],
        [
          [
            [
              17.375,
              5.6484375
            ],
            [
              0.0,
              25.0
            ]
          ]
        ],
        [
          [
            [
              -5.0,
              -8.59375
            ],
            [
              0.0,
              -37.5
            ]
          ]
        ],
        [
          [
            [
              5.75,
              5.765625
            ],
            [
              0.0,
              -12.5
            ]
          ]
        ],
        [
          [
            [
              1.75,
              -1.546875
            ],
            [
              0.0,
              12.5
            ]
          ]
        ],
        [
          [
            [
              0.5,
              -0.046875
            ],
            [
              0.0,
              -12.5
            ]
          ]
        ],
        [
          [
            [
              5.5,
              -5.625
            ],
            [
              0.0,
              37.5
            ]
          ]
        ],
        [
          [
            [
              1.125,
              -1.234375
            ],
            [
              0.0,
              12.5
            ]
          ]
        ],
        [],
        [],
        [],
        [],
        [],
        [],
        [],
        [],
        [],
        [],
        [],
        [],
        []
      ],
      "n_trials": 21,
      "n_remaining": 12,
      "kind": "non_repeating",
      "settings": {
        "kind": "standard",
        "targets_per_speaker": 3,
        "min_distance": 15,
        "mode": "all_sources_repeated",
        "repeats": 3,
        "azimuth_range": [
          0.0,
          0.0
        ],
        "elevation_range": [
          -37.5,
          37.5
        ],
        "sector_size": [
          10.0,
          12.5
        ],
        "sector_centers": [
          [
            5.0,
            -31.25
          ],
          [
            5.0,
            -18.75
          ],
          [
            5.0,
            -6.25
          ],
          [
            5.0,
            6.25
          ],
          [
            5.0,
            18.75
          ],
          [
            5.0,
            31.25
          ]
        ]
      },
      "name": "UG_16.06_09-42_dome",
      "stim": "pinknoise_burst"
    },
    "UG_16.06_09-44_dome": {
      "__class__": "slab.psychoacoustics.Trialsequence",
      "label": "",
      "n_reps": 1,
      "conditions": [
        [
          0.0,
          -37.5
        ],
        [
          0.0,
          12.5
        ],
        [
          0.0,
          -12.5
        ],
        [
          0.0,
          -37.5
        ],
        [
          0.0,
          -12.5
        ],
        [
          0.0,
          25.0
        ],
        [
          0.0,
          -25.0
        ],
        [
          0.0,
          12.5
        ],
        [
          0.0,
          -25.0
        ],
        [
          0.0,
          25.0
        ],
        [
          0.0,
          -25.0
        ],
        [
          0.0,
          37.5
        ],
        [
          0.0,
          0.0
        ],
        [
          0.0,
          25.0
        ],
        [
          0.0,
          0.0
        ],
        [
          0.0,
          37.5
        ],
        [
          0.0,
          -37.5
        ],
        [
          0.0,
          0.0
        ],
        [
          0.0,
          37.5
        ],
        [
          0.0,
          -12.5
        ],
        [
          0.0,
          12.5
        ]
      ],
      "n_conditions": 21,
      "trials": [
        1,
        2,
        3,
        4,
        5,
        6,
        7,
        8,
        9,
        10,
        11,
        12,
        13,
        14,
        15,
        16,
        17,
        18,
        19,
        20,
        21
      ],
      "this_n": 21,
      "this_trial": [],
      "finished": true,
      "data": [
        [
          [
            [
              4.25,
              -21.375
            ],
            [
              0.0,
              -37.5
            ]
          ]
        ],
        [
          [
            [
              -2.5,
              14.171875
            ],
            [
              0.0,
              12.5
            ]
          ]
        ],
        [
          [
            [
              -0.75,
              4.9453125
            ],
            [
              0.0,
              -12.5
            ]
          ]
        ],
        [
          [
            [
              11.0,
              -29.046875
            ],
            [
              0.0,
              -37.5
            ]
          ]
        ],
        [
          [
            [
              -0.5,
              7.0390625
            ],
            [
              0.0,
              -12.5
            ]
          ]
        ],
        [
          [
            [
              -2.25,
              17.1875
            ],
            [
              0.0,
              25.0
            ]
          ]
        ],
        [
          [
            [
              1.0,
              -14.0625
            ],
            [
              0.0,
              -25.0
            ]
          ]
        ],
        [
          [
            [
              -0.75,
              14.546875
            ],
            [
              0.0,
              12.5
            ]
          ]
        ],
        [
          [
            [
              -1.25,
              -14.0390625
            ],
            [
              0.0,
              -25.0
            ]
          ]
        ],
        [
          [
            [
              -0.5,
              19.625
            ],
            [
              0.0,
              25.0
            ]
          ]
        ],
        [
          [
            [
              -0.75,
              -4.76171875
            ],
            [
              0.0,
              -25.0
            ]
          ]
        ],
        [
          [
            [
              1.0,
              28.078125
            ],
            [
              0.0,
              37.5
            ]
          ]
        ],
        [
          [
            [
              -0.75,
              5.6484375
            ],
            [
              0.0,
              0.0
            ]
          ]
        ],
        [
          [
            [
              -0.75,
              16.109375
            ],
            [
              0.0,
              25.0
            ]
          ]
        ],
        [
          [
            [
              0.25,
              5.10546875
            ],
            [
              0.0,
              0.0
            ]
          ]
        ],
        [
          [
            [
              -1.0,
              13.234375
            ],
            [
              0.0,
              37.5
            ]
          ]
        ],
        [
          [
            [
              -2.25,
              -36.375
            ],
            [
              0.0,
              -37.5
            ]
          ]
        ],
        [
          [
            [
              -0.25,
              5.484375
            ],
            [
              0.0,
              0.0
            ]
          ]
        ],
        [
          [
            [
              0.75,
              29.65625
            ],
            [
              0.0,
              37.5
            ]
          ]
        ],
        [
          [
            [
              -0.5,
              2.2109375
            ],
            [
              0.0,
              -12.5
            ]
          ]
        ],
        [
          [
            [
              -0.25,
              9.5625
            ],
            [
              0.0,
              12.5
            ]
          ]
        ]
      ],
      "n_trials": 21,
      "n_remaining": -1,
      "kind": "non_repeating",
      "settings": {
        "kind": "standard",
        "targets_per_speaker": 3,
        "min_distance": 15,
        "mode": "all_sources_repeated",
        "repeats": 3,
        "azimuth_range": [
          0.0,
          0.0
        ],
        "elevation_range": [
          -37.5,
          37.5
        ],
        "sector_size": [
          10.0,
          12.5
        ],
        "sector_centers": [
          [
            5.0,
            -31.25
          ],
          [
            5.0,
            -18.75
          ],
          [
            5.0,
            -6.25
          ],
          [
            5.0,
            6.25
          ],
          [
            5.0,
            18.75
          ],
          [
            5.0,
            31.25
          ]
        ]
      },
      "name": "UG_16.06_09-44_dome",
      "stim": "pinknoise_burst"
    },
    "UG_16.06_09-48_dome": {
      "__class__": "slab.psychoacoustics.Trialsequence",
      "label": "",
      "n_reps": 1,
      "conditions": [
        [
          0.0,
          12.5
        ],
        [
          0.0,
          -12.5
        ],
        [
          0.0,
          25.0
        ],
        [
          0.0,
          -37.5
        ],
        [
          0.0,
          37.5
        ],
        [
          0.0,
          12.5
        ],
        [
          0.0,
          -37.5
        ],
        [
          0.0,
          -12.5
        ],
        [
          0.0,
          12.5
        ],
        [
          0.0,
          -25.0
        ],
        [
          0.0,
          25.0
        ],
        [
          0.0,
          0.0
        ],
        [
          0.0,
          25.0
        ],
        [
          0.0,
          -25.0
        ],
        [
          0.0,
          0.0
        ],
        [
          0.0,
          37.5
        ],
        [
          0.0,
          -37.5
        ],
        [
          0.0,
          0.0
        ],
        [
          0.0,
          -25.0
        ],
        [
          0.0,
          37.5
        ],
        [
          0.0,
          -12.5
        ]
      ],
      "n_conditions": 21,
      "trials": [
        1,
        2,
        3,
        4,
        5,
        6,
        7,
        8,
        9,
        10,
        11,
        12,
        13,
        14,
        15,
        16,
        17,
        18,
        19,
        20,
        21
      ],
      "this_n": 21,
      "this_trial": [],
      "finished": true,
      "data": [
        [
          [
            [
              -0.125,
              14.890625
            ],
            [
              0.0,
              12.5
            ]
          ]
        ],
        [
          [
            [
              -0.625,
              8.9921875
            ],
            [
              0.0,
              -12.5
            ]
          ]
        ],
        [
          [
            [
              0.375,
              23.734375
            ],
            [
              0.0,
              25.0
            ]
          ]
        ],
        [
          [
            [
              -0.125,
              -27.234375
            ],
            [
              0.0,
              -37.5
            ]
          ]
        ],
        [
          [
            [
              0.875,
              30.75
            ],
            [
              0.0,
              37.5
            ]
          ]
        ],
        [
          [
            [
              0.0,
              18.40625
            ],
            [
              0.0,
              12.5
            ]
          ]
        ],
        [
          [
            [
              0.0,
              -26.390625
            ],
            [
              0.0,
              -37.5
            ]
          ]
        ],
        [
          [
            [
              0.0,
              7.515625
            ],
            [
              0.0,
              -12.5
            ]
          ]
        ],
        [
          [
            [
              -0.5,
              17.15625
            ],
            [
              0.0,
              12.5
            ]
          ]
        ],
        [
          [
            [
              -1.0,
              -10.703125
            ],
            [
              0.0,
              -25.0
            ]
          ]
        ],
        [
          [
            [
              0.0,
              23.0
            ],
            [
              0.0,
              25.0
            ]
          ]
        ],
        [
          [
            [
              -1.0,
              8.65625
            ],
            [
              0.0,
              0.0
            ]
          ]
        ],
        [
          [
            [
              0.0,
              19.75
            ],
            [
              0.0,
              25.0
            ]
          ]
        ],
        [
          [
            [
              -2.0,
              -21.015625
            ],
            [
              0.0,
              -25.0
            ]
          ]
        ],
        [
          [
            [
              0.0,
              15.15625
            ],
            [
              0.0,
              0.0
            ]
          ]
        ],
        [
          [
            [
              2.0,
              34.25
            ],
            [
              0.0,
              37.5
            ]
          ]
        ],
        [
          [
            [
              -1.5,
              -44.3125
            ],
            [
              0.0,
              -37.5
            ]
          ]
        ],
        [
          [
            [
              0.875,
              11.453125
            ],
            [
              0.0,
              0.0
            ]
          ]
        ],
        [
          [
            [
              -1.0,
              -16.703125
            ],
            [
              0.0,
              -25.0
            ]
          ]
        ],
        [
          [
            [
              0.875,
              23.78125
            ],
            [
              0.0,
              37.5
            ]
          ]
        ],
        [
          [
            [
              -0.125,
              -7.453125
            ],
            [
              0.0,
              -12.5
            ]
          ]
        ]
      ],
      "n_trials": 21,
      "n_remaining": -1,
      "kind": "non_repeating",
      "settings": {
        "kind": "standard",
        "targets_per_speaker": 3,
        "min_distance": 15,
        "mode": "all_sources_repeated",
        "repeats": 3,
        "azimuth_range": [
          0.0,
          0.0
        ],
        "elevation_range": [
          -37.5,
          37.5
        ],
        "sector_size": [
          10.0,
          12.5
        ],
        "sector_centers": [
          [
            5.0,
            -31.25
          ],
          [
            5.0,
            -18.75
          ],
          [
            5.0,
            -6.25
          ],
          [
            5.0,
            6.25
          ],
          [
            5.0,
            18.75
          ],
          [
            5.0,
            31.25
          ]
        ]
      },
      "name": "UG_16.06_09-48_dome",
      "stim": "pinknoise_burst"
    },
    "UG_16.06_09-54_UG": {
      "__class__": "slab.psychoacoustics.Trialsequence",
      "label": "",
      "n_reps": 1,
      "conditions": [
        [
          0.0,
          0.0
        ],
        [
          0.0,
          -20.83
        ],
        [
          0.0,
          12.5
        ],
        [
          0.0,
          33.34
        ],
        [
          0.0,
          -20.83
        ],
        [
          0.0,
          0.0
        ],
        [
          0.0,
          16.67
        ],
        [
          0.0,
          -25.0
        ],
        [
          0.0,
          33.34
        ],
        [
          0.0,
          8.33
        ],
        [
          0.0,
          -8.33
        ],
        [
          0.0,
          12.5
        ],
        [
          0.0,
          -16.67
        ],
        [
          0.0,
          4.17
        ],
        [
          0.0,
          -12.5
        ],
        [
          0.0,
          8.33
        ],
        [
          0.0,
          25.0
        ],
        [
          0.0,
          -4.17
        ],
        [
          0.0,
          -33.34
        ],
        [
          0.0,
          25.0
        ],
        [
          0.0,
          -12.5
        ],
        [
          0.0,
          20.83
        ],
        [
          0.0,
          -4.17
        ],
        [
          0.0,
          16.67
        ],
        [
          0.0,
          -29.17
        ],
        [
          0.0,
          29.17
        ],
        [
          0.0,
          -8.33
        ],
        [
          0.0,
          29.17
        ],
        [
          0.0,
          -16.67
        ],
        [
          0.0,
          -33.34
        ],
        [
          0.0,
          4.17
        ],
        [
          0.0,
          -25.0
        ],
        [
          0.0,
          20.83
        ],
        [
          0.0,
          -29.17
        ]
      ],
      "n_conditions": 34,
      "trials": [
        1,
        2,
        3,
        4,
        5,
        6,
        7,
        8,
        9,
        10,
        11,
        12,
        13,
        14,
        15,
        16,
        17,
        18,
        19,
        20,
        21,
        22,
        23,
        24,
        25,
        26,
        27,
        28,
        29,
        30,
        31,
        32,
        33,
        34
      ],
      "this_n": 34,
      "this_trial": [],
      "finished": true,
      "data": [
        [
          [
            [
              0.0,
              4.25
            ],
            [
              0.0,
              0.0
            ]
          ]
        ],
        [
          [
            [
              0.25,
              -4.1796875
            ],
            [
              0.0,
              -20.83
            ]
          ]
        ],
        [
          [
            [
              -0.75,
              6.109375
            ],
            [
              0.0,
              12.5
            ]
          ]
        ],
        [
          [
            [
              -1.5,
              13.6796875
            ],
            [
              0.0,
              33.34
            ]
          ]
        ],
        [
          [
            [
              1.125,
              -17.953125
            ],
            [
              0.0,
              -20.83
            ]
          ]
        ],
        [
          [
            [
              -0.25,
              3.1171875
            ],
            [
              0.0,
              0.0
            ]
          ]
        ],
        [
          [
            [
              -1.25,
              7.0625
            ],
            [
              0.0,
              16.67
            ]
          ]
        ],
        [
          [
            [
              0.5,
              -11.125
            ],
            [
              0.0,
              -25.0
            ]
          ]
        ],
        [
          [
            [
              -1.25,
              11.375
            ],
            [
              0.0,
              33.34
            ]
          ]
        ],
        [
          [
            [
              -0.25,
              1.1171875
            ],
            [
              0.0,
              8.33
            ]
          ]
        ],
        [
          [
            [
              -0.625,
              7.19921875
            ],
            [
              0.0,
              -8.33
            ]
          ]
        ],
        [
          [
            [
              -0.5,
              7.19921875
            ],
            [
              0.0,
              12.5
            ]
          ]
        ],
        [
          [
            [
              0.625,
              -14.0234375
            ],
            [
              0.0,
              -16.67
            ]
          ]
        ],
        [
          [
            [
              -0.25,
              4.00390625
            ],
            [
              0.0,
              4.17
            ]
          ]
        ],
        [
          [
            [
              0.0,
              -1.8203125
            ],
            [
              0.0,
              -12.5
            ]
          ]
        ],
        [
          [
            [
              0.0,
              3.98828125
            ],
            [
              0.0,
              8.33
            ]
          ]
        ],
        [
          [
            [
              0.25,
              -3.2734375
            ],
            [
              0.0,
              25.0
            ]
          ]
        ],
        [
          [
            [
              0.375,
              -10.34375
            ],
            [
              0.0,
              -4.17
            ]
          ]
        ],
        [
          [
            [
              1.875,
              -25.828125
            ],
            [
              0.0,
              -33.34
            ]
          ]
        ],
        [
          [
            [
              -1.5,
              17.0625
            ],
            [
              0.0,
              25.0
            ]
          ]
        ],
        [
          [
            [
              1.5,
              -23.28125
            ],
            [
              0.0,
              -12.5
            ]
          ]
        ],
        [
          [
            [
              -1.875,
              18.6875
            ],
            [
              0.0,
              20.83
            ]
          ]
        ],
        [
          [
            [
              -1.125,
              9.109375
            ],
            [
              0.0,
              -4.17
            ]
          ]
        ],
        [
          [
            [
              -0.25,
              4.22265625
            ],
            [
              0.0,
              16.67
            ]
          ]
        ],
        [
          [
            [
              1.625,
              -27.03125
            ],
            [
              0.0,
              -29.17
            ]
          ]
        ],
        [
          [
            [
              -0.375,
              3.8359375
            ],
            [
              0.0,
              29.17
            ]
          ]
        ],
        [
          [
            [
              0.5,
              -6.2890625
            ],
            [
              0.0,
              -8.33
            ]
          ]
        ],
        [
          [
            [
              -0.875,
              8.9296875
            ],
            [
              0.0,
              29.17
            ]
          ]
        ],
        [
          [
            [
              0.75,
              -16.71875
            ],
            [
              0.0,
              -16.67
            ]
          ]
        ],
        [
          [
            [
              -0.125,
              0.75
            ],
            [
              0.0,
              -33.34
            ]
          ]
        ],
        [
          [
            [
              -0.5,
              3.56640625
            ],
            [
              0.0,
              4.17
            ]
          ]
        ],
        [
          [
            [
              0.875,
              -11.453125
            ],
            [
              0.0,
              -25.0
            ]
          ]
        ],
        [
          [
            [
              -1.875,
              18.21875
            ],
            [
              0.0,
              20.83
            ]
          ]
        ],
        [
          [
            [
              0.75,
              -12.0390625
            ],
            [
              0.0,
              -29.17
            ]
          ]
        ]
      ],
      "n_trials": 34,
      "n_remaining": -1,
      "kind": "non_repeating",
      "settings": {
        "kind": "standard",
        "azimuth_range": [
          -1,
          1
        ],
        "elevation_range": [
          -35,
          35
        ],
        "targets_per_speaker": 2,
        "min_distance": 15,
        "gain": 0.2,
        "stim": "noise",
        "mode": "all_sources_repeated",
        "repeats": 2,
        "sector_size": [
          2.0,
          4.156199999999998
        ],
        "sector_centers": [
          [
            0.0,
            -32.9219
          ],
          [
            0.0,
            -28.765700000000002
          ],
          [
            0.0,
            -24.609500000000004
          ],
          [
            0.0,
            -20.453300000000006
          ],
          [
            0.0,
            -16.297100000000007
          ],
          [
            0.0,
            -12.14090000000001
          ],
          [
            0.0,
            -7.984700000000011
          ],
          [
            0.0,
            -3.8285000000000124
          ],
          [
            0.0,
            0.3276999999999859
          ],
          [
            0.0,
            4.483899999999984
          ],
          [
            0.0,
            8.640099999999983
          ],
          [
            0.0,
            12.796299999999981
          ],
          [
            0.0,
            16.95249999999998
          ],
          [
            0.0,
            21.108699999999978
          ],
          [
            0.0,
            25.264899999999976
          ],
          [
            0.0,
            29.421099999999967
          ],
          [
            0.0,
            33.57729999999998
          ]
        ]
      },
      "name": "UG_16.06_09-54_UG",
      "hrir": "UG",
      "ear": null,
      "mirrored": false,
      "stim": "noise",
      "hp": "DT990",
      "response_errors": [
        [
          0.0,
          -32.9219,
          24.683560987179558,
          0.12948898356983313
        ],
        [
          0.0,
          -28.765700000000002,
          12.207441812095734,
          0.06403975638106578
        ],
        [
          0.0,
          -24.609500000000004,
          13.711919035379859,
          0.07193218432321767
        ],
        [
          0.0,
          -20.453300000000006,
          11.94799807736177,
          0.06267872482157112
        ],
        [
          0.0,
          -16.297100000000007,
          1.871719747839705,
          0.009818967684655842
        ],
        [
          0.0,
          -12.14090000000001,
          10.73058890881941,
          0.05629224452786377
        ],
        [
          0.0,
          -7.984700000000011,
          11.075244034879272,
          0.05810029167222857
        ],
        [
          0.0,
          -3.8285000000000124,
          10.355119252165206,
          0.054322545576131503
        ],
        [
          0.0,
          0.3276999999999859,
          3.7268859594946186,
          0.01955109617393917
        ],
        [
          0.0,
          4.483899999999984,
          0.4426694866534878,
          0.002322226599067773
        ],
        [
          0.0,
          8.640099999999983,
          5.952948255455351,
          0.031228930835510055
        ],
        [
          0.0,
          12.796299999999981,
          5.871046318629098,
          0.030799276517904078
        ],
        [
          0.0,
          16.95249999999998,
          11.118462633850601,
          0.058327014731150914
        ],
        [
          0.0,
          21.108699999999978,
          2.388402479953911,
          0.012529464838786183
        ],
        [
          0.0,
          25.264899999999976,
          20.765249508691273,
          0.1089336767029274
        ],
        [
          0.0,
          29.421099999999967,
          22.929075132368105,
          0.12028502024601677
        ],
        [
          0.0,
          33.57729999999998,
          20.844533007453734,
          0.10934959479813026
        ]
      ]
    }
  }
}